{
  "avail": [],
  "codes": [
    {
      "code": "BLAK"
    }
  ],
  "known": [],
  "links": [
    {
      "type": "art",
      "url": "otrr.org/piwigo/upload/2021/03/22/20210322164236-37985896.jpg",
      "label": "Black Adder",
      "idtype": "12"
    }
  ],
  "infos": [],
  "people": [],
  "prints": [],
  "synopses": [],
  "themes": [],
  "episodes": [
    {
      "ide": "34358",
      "date": "1983-06-15",
      "epnum": "101",
      "exists": "1",
      "titles": [
        {
          "title": "Foretelling"
        }
      ],
      "files": []
    },
    {
      "ide": "34359",
      "date": "1983-06-22",
      "epnum": "102",
      "exists": "1",
      "titles": [
        {
          "title": "Queen of Spain's Beard"
        }
      ],
      "files": []
    },
    {
      "ide": "34360",
      "date": "1983-06-29",
      "epnum": "103",
      "exists": "1",
      "titles": [
        {
          "title": "Archbishop"
        }
      ],
      "files": []
    },
    {
      "ide": "34361",
      "date": "1983-07-06",
      "epnum": "104",
      "exists": "1",
      "titles": [
        {
          "title": "Born to Be King"
        }
      ],
      "files": []
    },
    {
      "ide": "34362",
      "date": "1983-07-13",
      "epnum": "105",
      "exists": "1",
      "titles": [
        {
          "title": "Witchsmeller Persuivant"
        }
      ],
      "files": []
    },
    {
      "ide": "34363",
      "date": "1983-07-20",
      "epnum": "106",
      "exists": "1",
      "titles": [
        {
          "title": "Black Seal"
        }
      ],
      "files": []
    },
    {
      "ide": "34364",
      "date": "1986-01-09",
      "epnum": "201",
      "exists": "1",
      "titles": [
        {
          "title": "Bells"
        }
      ],
      "files": []
    },
    {
      "ide": "34365",
      "date": "1986-01-16",
      "epnum": "202",
      "exists": "1",
      "titles": [
        {
          "title": "Head"
        }
      ],
      "files": []
    },
    {
      "ide": "34366",
      "date": "1986-01-23",
      "epnum": "203",
      "exists": "1",
      "titles": [
        {
          "title": "Potato"
        }
      ],
      "files": []
    },
    {
      "ide": "34367",
      "date": "1986-02-06",
      "epnum": "204",
      "exists": "1",
      "titles": [
        {
          "title": "Money"
        }
      ],
      "files": []
    },
    {
      "ide": "34368",
      "date": "1986-02-13",
      "epnum": "205",
      "exists": "1",
      "titles": [
        {
          "title": "Beer"
        }
      ],
      "files": []
    },
    {
      "ide": "34369",
      "date": "1986-02-20",
      "epnum": "206",
      "exists": "1",
      "titles": [
        {
          "title": "Chains"
        }
      ],
      "files": []
    },
    {
      "ide": "34370",
      "date": "1987-09-17",
      "epnum": "301",
      "exists": "1",
      "titles": [
        {
          "title": "Dish & Dishonesty"
        }
      ],
      "files": []
    },
    {
      "ide": "34371",
      "date": "1987-09-24",
      "epnum": "302",
      "exists": "1",
      "titles": [
        {
          "title": "Ink and Incapability"
        }
      ],
      "files": []
    },
    {
      "ide": "34372",
      "date": "1987-10-01",
      "epnum": "303",
      "exists": "1",
      "titles": [
        {
          "title": "Nob & Nobility"
        }
      ],
      "files": []
    },
    {
      "ide": "34373",
      "date": "1987-10-08",
      "epnum": "304",
      "exists": "1",
      "titles": [
        {
          "title": "Sense & Senility"
        }
      ],
      "files": []
    },
    {
      "ide": "34374",
      "date": "1987-10-15",
      "epnum": "305",
      "exists": "1",
      "titles": [
        {
          "title": "Amy & Amiability"
        }
      ],
      "files": []
    },
    {
      "ide": "34375",
      "date": "1987-10-22",
      "epnum": "306",
      "exists": "1",
      "titles": [
        {
          "title": "Duel & Duality"
        }
      ],
      "files": []
    },
    {
      "ide": "34376",
      "date": "1988-02-05",
      "epnum": "307",
      "exists": "1",
      "titles": [
        {
          "title": "Cavalier Years, The"
        }
      ],
      "files": []
    },
    {
      "ide": "34377",
      "date": "1988-12-23",
      "epnum": "308",
      "exists": "1",
      "titles": [
        {
          "title": "Christmas Carol"
        }
      ],
      "files": []
    },
    {
      "ide": "34378",
      "date": "1989-09-29",
      "epnum": "401",
      "exists": "1",
      "titles": [
        {
          "title": "Captain Cook"
        }
      ],
      "files": []
    },
    {
      "ide": "34379",
      "date": "1989-10-05",
      "epnum": "402",
      "exists": "1",
      "titles": [
        {
          "title": "Corporal Punishment"
        }
      ],
      "files": []
    },
    {
      "ide": "34380",
      "date": "1989-10-12",
      "epnum": "403",
      "exists": "1",
      "titles": [
        {
          "title": "Major Star"
        }
      ],
      "files": []
    },
    {
      "ide": "34381",
      "date": "1989-10-19",
      "epnum": "404",
      "exists": "1",
      "titles": [
        {
          "title": "Private Plane"
        }
      ],
      "files": []
    },
    {
      "ide": "34382",
      "date": "1989-10-26",
      "epnum": "405",
      "exists": "1",
      "titles": [
        {
          "title": "General Hospital"
        }
      ],
      "files": []
    },
    {
      "ide": "34383",
      "date": "1989-11-02",
      "epnum": "406",
      "exists": "1",
      "titles": [
        {
          "title": "Goodbye"
        }
      ],
      "files": []
    }
  ],
  "genres": [
    {
      "genre": "Sitcom"
    }
  ],
  "histories": [],
  "sponsors": [],
  "titles": [
    {
      "title": "Black Adder"
    }
  ]
}
