{
  "avail": [],
  "codes": [],
  "known": [],
  "links": [
    {
      "type": "OTRR Library",
      "url": "/Library Files/A Series/A Crime Letter From Dan Dodge/",
      "label": "Library Files",
      "idtype": "15"
    },
    {
      "type": "web",
      "url": "www.goldenage-wtic.org/gaor-24.html",
      "label": "The Golden Age of Radio: Program 24 - March, 1972 - Shirley Eggleston",
      "idtype": "1"
    },
    {
      "type": "web",
      "url": "www.thrillingdetective.com/dodge.html",
      "label": "Thrilling Detective",
      "idtype": "1"
    }
  ],
  "infos": [],
  "people": [
    {
      "idperson": "3986",
      "first": "Myron",
      "last": "McCormick",
      "f": "Noted Role",
      "character": "Dan Dodge"
    },
    {
      "idperson": "7309",
      "first": "Shirley",
      "last": "Eggleston",
      "f": "Noted Role",
      "character": "His Secretary"
    }
  ],
  "prints": [
    {
      "idprint": "2780",
      "idtype": "5",
      "page": "",
      "article": "",
      "url": "",
      "date": "0000-00-00",
      "source": "",
      "idpytype2": "5",
      "title": "4th Revised Ultimate History of Network Radio Programming and Guide to ALL Circulating Shows, The",
      "author": "Hickerson, Jay"
    },
    {
      "idprint": "757",
      "idtype": "4",
      "page": "4",
      "article": "",
      "url": "",
      "date": "1998-04-01",
      "source": "Illustrated Press/IP_259.pdf",
      "idpytype2": "4",
      "title": "Illustrated Press (#259) - Apr 1998",
      "author": ""
    },
    {
      "idprint": "83",
      "idtype": "1",
      "page": "",
      "article": "",
      "url": "",
      "date": "1929-03-17",
      "source": "New York Times",
      "idpytype2": "2",
      "title": "RADIO PROGRAMS SCHEDULED FOR THE CURRENT WEEK",
      "author": ""
    },
    {
      "idprint": "42",
      "idtype": "1",
      "page": "",
      "article": "",
      "url": "",
      "date": "1929-12-29",
      "source": "New York Times",
      "idpytype2": "2",
      "title": "RADIO PROGRAMS SCHEDULED FOR THE CURRENT WEEK New York",
      "author": ""
    },
    {
      "idprint": "2821",
      "idtype": "5",
      "page": "",
      "article": "",
      "url": "",
      "date": "0000-00-00",
      "source": "Collector's Corner",
      "idpytype2": "5",
      "title": "Radio's Golden Years - The Encyclopedia of Radio Programs 1930-1960",
      "author": "Terrace, Vincent"
    }
  ],
  "synopses": [],
  "themes": [],
  "episodes": [
    {
      "ide": "50818",
      "date": "1952-10-24",
      "epnum": "1",
      "exists": "0",
      "titles": [
        {
          "title": "[PREMIERE (w Myron McCormick)]"
        }
      ],
      "files": []
    },
    {
      "ide": "50819",
      "date": "1952-10-31",
      "epnum": "2",
      "exists": "0",
      "titles": [],
      "files": []
    },
    {
      "ide": "50820",
      "date": "1952-11-07",
      "epnum": "3",
      "exists": "0",
      "titles": [
        {
          "title": "Cheesecake Crime Letter, The"
        }
      ],
      "files": []
    },
    {
      "ide": "50821",
      "date": "1952-11-14",
      "epnum": "4",
      "exists": "0",
      "titles": [],
      "files": []
    },
    {
      "ide": "50822",
      "date": "1952-11-21",
      "epnum": "5",
      "exists": "0",
      "titles": [
        {
          "title": "Martin Blake Caper, The"
        }
      ],
      "files": []
    },
    {
      "ide": "50823",
      "date": "1952-11-28",
      "epnum": "6",
      "exists": "0",
      "titles": [
        {
          "title": "Silver Key Caper, The"
        }
      ],
      "files": []
    },
    {
      "ide": "50824",
      "date": "1952-12-05",
      "epnum": "7",
      "exists": "0",
      "titles": [
        {
          "title": "Flashback Caper, The"
        }
      ],
      "files": []
    },
    {
      "ide": "50825",
      "date": "1952-12-12",
      "epnum": "8",
      "exists": "0",
      "titles": [
        {
          "title": "Peacock Feather Caper, The"
        }
      ],
      "files": []
    },
    {
      "ide": "50826",
      "date": "1952-12-19",
      "epnum": "9",
      "exists": "0",
      "titles": [
        {
          "title": "Whispering Death Caper, The"
        }
      ],
      "files": []
    },
    {
      "ide": "50827",
      "date": "1952-12-26",
      "epnum": "10",
      "exists": "0",
      "titles": [],
      "files": []
    },
    {
      "ide": "50828",
      "date": "1953-01-02",
      "epnum": "11",
      "exists": "0",
      "titles": [
        {
          "title": "Phantom Witness Caper, The"
        }
      ],
      "files": []
    },
    {
      "ide": "50829",
      "date": "1953-01-09",
      "epnum": "12",
      "exists": "0",
      "titles": [
        {
          "title": "Old Black Magic Caper (pulls a rabbit and a crook out of his hat), The"
        }
      ],
      "files": []
    },
    {
      "ide": "50830",
      "date": "1953-01-16",
      "epnum": "13",
      "exists": "0",
      "titles": [],
      "files": []
    },
    {
      "ide": "50831",
      "date": "1953-01-23",
      "epnum": "14",
      "exists": "0",
      "titles": [
        {
          "title": "Wedding Bell Caper, The"
        }
      ],
      "files": []
    },
    {
      "ide": "50832",
      "date": "1953-01-30",
      "epnum": "15",
      "exists": "1",
      "titles": [
        {
          "title": "Runaway Redhead Caper, The"
        }
      ],
      "files": [
        {
          "path": "C",
          "folder": "Crime Letter From Dan Dodge",
          "name": "A Crime Letter From Dan Dodge xx-xx-xx The Runaway Redhead Caper - Progam1.mp3",
          "time": "582",
          "size": "9316311"
        }
      ]
    },
    {
      "ide": "50833",
      "date": "1953-02-06",
      "epnum": "16",
      "exists": "0",
      "titles": [
        {
          "title": "Buried Groom Caper, The"
        }
      ],
      "files": []
    },
    {
      "ide": "50834",
      "date": "1953-02-13",
      "epnum": "17",
      "exists": "0",
      "titles": [
        {
          "title": "Femme Fatale Caper, The"
        }
      ],
      "files": []
    },
    {
      "ide": "50835",
      "date": "1953-02-20",
      "epnum": "18",
      "exists": "1",
      "titles": [
        {
          "title": "Preposterous Caper (newspaper headline 'Escaped Lunatic Seeks Private Detective' lures Dan Dodge), The"
        }
      ],
      "files": [
        {
          "path": "C",
          "folder": "Crime Letter From Dan Dodge",
          "name": "A Crime Letter From Dan Dodge xx-xx-xx The Preposterous Cape - Progam2.mp3",
          "time": "501",
          "size": "8021473"
        }
      ]
    },
    {
      "ide": "50836",
      "date": "1953-02-27",
      "epnum": "19",
      "exists": "0",
      "titles": [
        {
          "title": "Prodigal Panda Caper (Last Episode), The"
        }
      ],
      "files": []
    }
  ],
  "genres": [
    {
      "genre": "Private Detective"
    },
    {
      "genre": "Crime"
    },
    {
      "genre": "Drama"
    }
  ],
  "histories": [
    {
      "begin": "1952-10-31",
      "dow": "F",
      "time": "8:00 PM",
      "end": "1953-02-27",
      "length": "30",
      "country": "USA",
      "network": "ABC"
    }
  ],
  "sponsors": [],
  "titles": [
    {
      "title": "Crime Letter from Dan Dodge, A"
    }
  ]
}
