{
  "avail": [],
  "codes": [],
  "known": [],
  "links": [],
  "infos": [
    {
      "info": "Hickerson writes ';On various dates and times including'; those listed. - In his book, Music Radio, Jim Cox Music for Today was aka Morton Gould Orchestra for many years."
    }
  ],
  "people": [
    {
      "idperson": "107",
      "first": "Jack",
      "last": "Arthur",
      "f": "Cast Member",
      "character": ""
    },
    {
      "idperson": "2310",
      "first": "Morton",
      "last": "Gould",
      "f": "Musician",
      "character": ""
    },
    {
      "idperson": "50216",
      "first": "Jimmie",
      "last": "Shields",
      "f": "Cast Member",
      "character": ""
    },
    {
      "idperson": "3769",
      "first": "Elaine",
      "last": "Malbin",
      "f": "Noted Role",
      "character": "Vocalist"
    }
  ],
  "prints": [
    {
      "idprint": "4413",
      "idtype": "1",
      "page": "",
      "article": "",
      "url": "",
      "date": "0000-00-00",
      "source": "",
      "idpytype2": "5",
      "title": "5th Revised Ultimate History of Network Radio Programming and Guide to ALL Circulating Shows, The",
      "author": "Hickerson, Jay"
    },
    {
      "idprint": "2780",
      "idtype": "5",
      "page": "",
      "article": "",
      "url": "",
      "date": "0000-00-00",
      "source": "",
      "idpytype2": "5",
      "title": "4th Revised Ultimate History of Network Radio Programming and Guide to ALL Circulating Shows, The",
      "author": "Hickerson, Jay"
    },
    {
      "idprint": "710",
      "idtype": "4",
      "page": "14",
      "article": "",
      "url": "",
      "date": "1976-10-01",
      "source": "Illustrated Press/IP_005.pdf",
      "idpytype2": "4",
      "title": "Illustrated Press (#005) - Oct 1976",
      "author": ""
    },
    {
      "idprint": "42",
      "idtype": "1",
      "page": "",
      "article": "",
      "url": "",
      "date": "1929-12-29",
      "source": "New York Times",
      "idpytype2": "2",
      "title": "RADIO PROGRAMS SCHEDULED FOR THE CURRENT WEEK New York",
      "author": ""
    }
  ],
  "synopses": [],
  "themes": [],
  "episodes": [],
  "genres": [
    {
      "genre": "Music"
    }
  ],
  "histories": [
    {
      "begin": "1936-12-06",
      "dow": "Su",
      "time": "8:00 PM",
      "end": "1937-00-00",
      "length": "30",
      "country": "USA",
      "network": "Mutual"
    },
    {
      "begin": "1937-00-00",
      "dow": "M",
      "time": "",
      "end": "1938-00-00",
      "length": "30",
      "country": "USA",
      "network": "Mutual"
    },
    {
      "begin": "1938-00-00",
      "dow": "Tu",
      "time": "8:30 PM",
      "end": "1940-01-30",
      "length": "30",
      "country": "USA",
      "network": "Mutual"
    },
    {
      "begin": "1940-02-05",
      "dow": "M",
      "time": "9:30 PM",
      "end": "1940-05-13",
      "length": "30",
      "country": "USA",
      "network": "Mutual"
    },
    {
      "begin": "1940-05-16",
      "dow": "Th",
      "time": "9:30 PM",
      "end": "1940-08-29",
      "length": "30",
      "country": "USA",
      "network": "Mutual"
    },
    {
      "begin": "1940-09-05",
      "dow": "Th",
      "time": "10:30 PM",
      "end": "1940-10-31",
      "length": "30",
      "country": "USA",
      "network": "Mutual"
    },
    {
      "begin": "1940-09-14",
      "dow": "Tu",
      "time": "9:30 PM",
      "end": "1942-02-03",
      "length": "30",
      "country": "USA",
      "network": "Mutual"
    },
    {
      "begin": "1942-02-09",
      "dow": "M",
      "time": "8:30 PM",
      "end": "1942-05-18",
      "length": "30",
      "country": "USA",
      "network": "Mutual"
    },
    {
      "begin": "1942-07-13",
      "dow": "Tu",
      "time": "8:00 PM",
      "end": "1942-10-06",
      "length": "30",
      "country": "USA",
      "network": "Mutual"
    }
  ],
  "sponsors": [],
  "titles": [
    {
      "title": "Morton Gould Orchestra"
    },
    {
      "title": "Morton Gould Show, The"
    },
    {
      "title": "Music for Today"
    }
  ]
}
